pymultilang/__init__.py
pymultilang-1.1.1.dist-info/METADATA
pymultilang-1.1.1.dist-info/WHEEL
pymultilang-1.1.1.dist-info/top_level.txt
pymultilang-1.1.1.dist-info/RECORD
