Metadata-Version: 2.1
Name: pymultilang
Version: 1.1.1
Summary: Multi-language support for your project
Home-page: https://github.com/avestoinn/pymultilang
Author: Bekhruz Iskandarzoda
Author-email: avesto.inn@gmail.com
License: UNKNOWN
Platform: UNKNOWN
Requires-Python: >=3.6
